acasoenrichmentlib/__init__.py
acasoenrichmentlib/enrichment.py
classes/__init__.py
classes/googlesearch.py
classes/openai.py
classes/proxycurl.py
lib/__init__.py
lib/functions.py
processor/__init__.py
tests/__init__.py
tests/test_enrichment.py
acasoenrichmentlib-0.1.0.dist-info/METADATA
acasoenrichmentlib-0.1.0.dist-info/WHEEL
acasoenrichmentlib-0.1.0.dist-info/top_level.txt
acasoenrichmentlib-0.1.0.dist-info/RECORD
